{"cameraMode":{"drawMode":0,"name":"Shaded","section":"Shading Mode"},"sceneLighting":true,"audioPlay":false,"sceneViewState":{"m_AlwaysRefresh":false,"showFog":true,"showSkybox":true,"showFlares":true,"showImageEffects":true,"showParticleSystems":true,"showVisualEffectGraphs":true,"m_FxEnabled":true},"in2DMode":false,"pivot":{"x":67.95445251464844,"y":6.233304977416992,"z":113.05879211425781},"rotation":{"x":-0.060511164367198947,"y":0.9070795774459839,"z":0.13987646996974946,"w":0.3924090564250946},"size":3.9073946475982668,"orthographic":false}